pdp1/__init__.py
pdp1/main.py
pdp1-1.0.20100.44000.0.dist-info/METADATA
pdp1-1.0.20100.44000.0.dist-info/WHEEL
pdp1-1.0.20100.44000.0.dist-info/top_level.txt
pdp1-1.0.20100.44000.0.dist-info/RECORD
